video_grabber/FPS.py
video_grabber/__init__.py
video_grabber/image_misc.py
video_grabber/option_key_value.py
video_grabber/skeleton.py
video_grabber/video_grabber.py
video_grabber-0.1.0.dist-info/LICENSE.txt
video_grabber-0.1.0.dist-info/METADATA
video_grabber-0.1.0.dist-info/WHEEL
video_grabber-0.1.0.dist-info/entry_points.txt
video_grabber-0.1.0.dist-info/top_level.txt
video_grabber-0.1.0.dist-info/RECORD
