Metadata-Version: 2.1
Name: video-grabber
Version: 0.1.0
Summary: Utilities to load video from files or camera.
Home-page: https://github.com/arcayi/video_grabber
Author: arcayi
Author-email: arcayi@qq.com
License: CC0-1.0
Project-URL: Documentation, https://pyscaffold.org/
Platform: any
Classifier: Development Status :: 4 - Beta
Classifier: Programming Language :: Python
License-File: LICENSE.txt
Requires-Dist: importlib-metadata ; python_version < "3.8"
Provides-Extra: testing
Requires-Dist: setuptools ; extra == 'testing'
Requires-Dist: pytest ; extra == 'testing'
Requires-Dist: pytest-cov ; extra == 'testing'
